iolanta/__init__.py
iolanta/base_plugin.py
iolanta/cli/__init__.py
iolanta/cli/formatters/__init__.py
iolanta/cli/formatters/choose.py
iolanta/cli/formatters/csv.py
iolanta/cli/formatters/json.py
iolanta/cli/formatters/pretty.py
iolanta/cli/main.py
iolanta/cli/models.py
iolanta/cli/pretty_print.py
iolanta/context.py
iolanta/conversions.py
iolanta/data/context.yaml
iolanta/data/graph-triples.yamlld
iolanta/data/iolanta.yaml
iolanta/data/textual-browser.yaml
iolanta/declension/__init__.py
iolanta/declension/data/declension.yamlld
iolanta/declension/facet.py
iolanta/declension/sparql/declension.sparql
iolanta/ensure_is_context.py
iolanta/entry_points.py
iolanta/errors.py
iolanta/facets/__init__.py
iolanta/facets/cli/__init__.py
iolanta/facets/cli/base.py
iolanta/facets/cli/default.py
iolanta/facets/cli/record.py
iolanta/facets/cli/sparql/link.sparql
iolanta/facets/cli/sparql/record.sparql
iolanta/facets/errors.py
iolanta/facets/facet.py
iolanta/facets/foaf_person_title/__init__.py
iolanta/facets/foaf_person_title/facet.py
iolanta/facets/foaf_person_title/sparql/names.sparql
iolanta/facets/generic/__init__.py
iolanta/facets/generic/bool_literal.py
iolanta/facets/generic/date_literal.py
iolanta/facets/generic/default.py
iolanta/facets/generic/sparql/default.sparql
iolanta/facets/html/__init__.py
iolanta/facets/html/base.py
iolanta/facets/html/code_literal.py
iolanta/facets/html/default.py
iolanta/facets/icon.py
iolanta/facets/locator/sparql/get-query-to-facet.sparql
iolanta/facets/locator.py
iolanta/facets/mermaid_roadmap/__init__.py
iolanta/facets/mermaid_roadmap/facet.py
iolanta/facets/mermaid_roadmap/inference/blocks.sparql
iolanta/facets/mermaid_roadmap/inference/has-task-default-type.sparql
iolanta/facets/mermaid_roadmap/inference/task.sparql
iolanta/facets/mermaid_roadmap/inference/unblocked.sparql
iolanta/facets/mermaid_roadmap/mermaid_roadmap.yamlld
iolanta/facets/mermaid_roadmap/sparql/edges.sparql
iolanta/facets/mermaid_roadmap/sparql/nodes.sparql
iolanta-2.1.19.dist-info/METADATA
iolanta-2.1.19.dist-info/WHEEL
iolanta-2.1.19.dist-info/entry_points.txt
iolanta-2.1.19.dist-info/RECORD
